piwwwaterflow/__init__.py
piwwwaterflow/webservice.py
piwwwaterflow/wsgi.py
piwwwaterflow/__pycache__/__init__.cpython-38.pyc
piwwwaterflow/__pycache__/webservice.cpython-38.pyc
piwwwaterflow/static/__init__.py
piwwwaterflow/static/css/iepngfix.htc
piwwwaterflow/static/css/view.css
piwwwaterflow/static/img/blank.gif
piwwwaterflow/static/img/bottom.png
piwwwaterflow/static/img/icon-256.png
piwwwaterflow/static/img/icon-32.png
piwwwaterflow/static/img/piwaterflow.svg
piwwwaterflow/static/img/play.png
piwwwaterflow/static/img/shadow.gif
piwwwaterflow/static/img/top.png
piwwwaterflow/static/js/code.js
piwwwaterflow/templates/__init__.py
piwwwaterflow/templates/form.html
tests/__init__.py
piwwwaterflow-1.0.0.dist-info/METADATA
piwwwaterflow-1.0.0.dist-info/WHEEL
piwwwaterflow-1.0.0.dist-info/top_level.txt
piwwwaterflow-1.0.0.dist-info/RECORD
