Metadata-Version: 2.1
Name: piwwwaterflow
Version: 1.0.0
Summary: Raspberry Pi Waterflow resilient system
Home-page: https://github.com/Phornee/piwwwaterflow
Author: Ismael Raya
Author-email: phornee@gmail.com
License: UNKNOWN
Platform: UNKNOWN
Classifier: Programming Language :: Python :: 3
Classifier: License :: OSI Approved :: MIT License
Classifier: Operating System :: OS Independent
Classifier: Topic :: Home Automation
Requires-Python: >=3.6
Requires-Dist: Flask (>=1.1.2)
Requires-Dist: flask-compress (>=1.9.0)
Requires-Dist: importlib-metadata (>=4.5.0)
Requires-Dist: piwaterflow (>=1.0.0)
Requires-Dist: revproxy-auth (>=0.1.8)
